oreopy/__init__.py
oreopy/fields/__init__.py
oreopy/fields/integer_field.py
oreopy/fields/text_field.py
oreopy/models/__init__.py
oreopy/models/base.py
oreopy-0.0.3.dist-info/LICENSE
oreopy-0.0.3.dist-info/METADATA
oreopy-0.0.3.dist-info/WHEEL
oreopy-0.0.3.dist-info/top_level.txt
oreopy-0.0.3.dist-info/RECORD
