Metadata-Version: 2.1
Name: oreopy
Version: 0.0.3
Summary: Simple and fast ORM for python
Home-page: UNKNOWN
Author: Alexey Makridenko
Author-email: makridenko.a@yandex.ru
License: UNKNOWN
Platform: UNKNOWN
